noldor/__init__.py
noldor/_typevar.py
noldor/config.py
noldor/manage_attrs.py
noldor/py.typed
noldor/response.py
noldor/validate.py
noldor/validator.py
noldor/validators/__init__.py
noldor/validators/integer.py
noldor/validators/number.py
noldor/validators/sized.py
noldor-0.1.6.dist-info/LICENSE
noldor-0.1.6.dist-info/METADATA
noldor-0.1.6.dist-info/WHEEL
noldor-0.1.6.dist-info/RECORD
