Metadata-Version: 2.1
Name: noldor
Version: 0.1.6
Summary: A validation library easy to extend.
Home-page: https://gitea.nicheosala.xyz/nicheosala/noldor
License: MIT
Author: Nicolò Sala
Author-email: nicolo.sala@protonmail.com
Requires-Python: >=3.10,<4.0
Classifier: License :: OSI Approved :: MIT License
Classifier: Programming Language :: Python :: 3
Classifier: Programming Language :: Python :: 3.10
Classifier: Programming Language :: Python :: 3.11
Project-URL: Repository, https://gitea.nicheosala.xyz/nicheosala/noldor
